smsfusion/__about__.py
smsfusion/__init__.py
smsfusion/_ins.py
smsfusion/_smoothing.py
smsfusion/_transforms.py
smsfusion/_vectorops.py
smsfusion/benchmark/__init__.py
smsfusion/benchmark/_benchmark.py
smsfusion/calibrate/__init__.py
smsfusion/calibrate/_calibrate.py
smsfusion/constants/__init__.py
smsfusion/constants/_constants.py
smsfusion/noise/__init__.py
smsfusion/noise/_allan.py
smsfusion/noise/_noise.py
smsfusion-1.9.1.dist-info/METADATA
smsfusion-1.9.1.dist-info/WHEEL
smsfusion-1.9.1.dist-info/licenses/LICENSE
smsfusion-1.9.1.dist-info/RECORD
