Metadata-Version: 2.4
Name: smsfusion
Version: 1.9.1
Summary: Sensor fusion algorithms and utilities for SMS Motion
Project-URL: Homepage, https://github.com/4Subsea/smsfusion-python
Project-URL: Bug Tracker, https://github.com/4Subsea/smsfusion-python/issues
Author-email: 4Subsea <python@4subsea.com>
License-File: LICENSE
Classifier: License :: OSI Approved :: MIT License
Classifier: Operating System :: OS Independent
Classifier: Programming Language :: Python :: 3.11
Classifier: Programming Language :: Python :: 3.12
Classifier: Programming Language :: Python :: 3.13
Requires-Python: >=3.11
Requires-Dist: numba
Requires-Dist: numpy
Requires-Dist: scipy
